default_logging/__init__.py
default_logging/logging_config.py
default_logging/logging_config.yaml
default_logging/millisecond_formatter.py
default_logging-0.5.1.dist-info/LICENSE
default_logging-0.5.1.dist-info/METADATA
default_logging-0.5.1.dist-info/WHEEL
default_logging-0.5.1.dist-info/RECORD
