Metadata-Version: 2.3
Name: default_logging
Version: 0.5.1
Summary: A Python package that provides ready-to-use logging configuration with enhanced formatters, and automatic directory creation. Simplifies logging setup with sensible defaults while supporting custom configurations.
License: MIT
Author: kimberly
Author-email: 45748394+kquiet@users.noreply.github.com
Requires-Python: >=3.10
Classifier: License :: OSI Approved :: MIT License
Classifier: Programming Language :: Python :: 3
Classifier: Programming Language :: Python :: 3.10
Classifier: Programming Language :: Python :: 3.11
Classifier: Programming Language :: Python :: 3.12
Classifier: Programming Language :: Python :: 3.13
Requires-Dist: pyyaml (>=6.0.2,<7.0.0)
Project-URL: Repository, https://github.com/kquiet/python_default_logging
